spyder_vim/__init__.py
spyder_vim/spyder/__init__.py
spyder_vim/spyder/api.py
spyder_vim/spyder/confpage.py
spyder_vim/spyder/container.py
spyder_vim/spyder/plugin.py
spyder_vim/spyder/widgets.py
spyder_vim-0.1.0.dist-info/LICENSE.txt
spyder_vim-0.1.0.dist-info/METADATA
spyder_vim-0.1.0.dist-info/WHEEL
spyder_vim-0.1.0.dist-info/entry_points.txt
spyder_vim-0.1.0.dist-info/top_level.txt
spyder_vim-0.1.0.dist-info/RECORD
