Metadata-Version: 2.1
Name: spyder-vim
Version: 0.1.0
Summary: A plugin to enable vim keybindings to the spyder editor
Home-page: https://github.com/spyder-ide/spyder-vim
Author: Joseph Martinot-Lagarde and the spyder-vim contributors
Author-email: spyder.python@gmail.com
License: MIT license
Classifier: Operating System :: MacOS
Classifier: Operating System :: Microsoft :: Windows
Classifier: Operating System :: POSIX :: Linux
Classifier: Programming Language :: Python :: 3
Classifier: Programming Language :: Python :: 3.7
Classifier: Programming Language :: Python :: 3.8
Classifier: Programming Language :: Python :: 3.9
Classifier: Development Status :: 4 - Beta
Classifier: Intended Audience :: Education
Classifier: Intended Audience :: Science/Research
Classifier: Intended Audience :: Developers
Classifier: Topic :: Scientific/Engineering
Classifier: Topic :: Text Editors :: Integrated Development Environments (IDE)
Requires-Python: >= 3.7
License-File: LICENSE.txt
Requires-Dist: qtpy
Requires-Dist: qtawesome
Requires-Dist: spyder (>=5.3.3)
